legos.ctftime-0.1.0-py3.6-nspkg.pth
legos/ctftime.py
legos.ctftime-0.1.0.dist-info/DESCRIPTION.rst
legos.ctftime-0.1.0.dist-info/METADATA
legos.ctftime-0.1.0.dist-info/RECORD
legos.ctftime-0.1.0.dist-info/WHEEL
legos.ctftime-0.1.0.dist-info/metadata.json
legos.ctftime-0.1.0.dist-info/namespace_packages.txt
legos.ctftime-0.1.0.dist-info/top_level.txt
